kineticspy/__init__.py
kineticspy/graphics.py
kineticspy/kin.py
kineticspy/measure.py
kineticspy/solidobj.py
kineticspy/trajectory.py
kineticspy/robobj/__init__.py
kineticspy/robobj/robot.py
kineticspy-0.0.1.dist-info/LICENSE
kineticspy-0.0.1.dist-info/METADATA
kineticspy-0.0.1.dist-info/WHEEL
kineticspy-0.0.1.dist-info/top_level.txt
kineticspy-0.0.1.dist-info/RECORD
