Metadata-Version: 2.1
Name: kineticspy
Version: 0.0.1
Summary: A small package for robot simulation
Home-page: https://github.com/Kaneki99/simulpy
Author: Arjun Sahdev
Author-email: arjunsahdev13@gmail.com
License: UNKNOWN
Platform: UNKNOWN
Classifier: Programming Language :: Python :: 3
Classifier: License :: OSI Approved :: MIT License
Classifier: Operating System :: OS Independent
